secomlint/__init__.py
secomlint/__main__.py
secomlint/config.py
secomlint/extractor.py
secomlint/message.py
secomlint/parser.py
secomlint/rule.py
secomlint/ruler.py
secomlint/section.py
secomlint/utils.py
secomlint/config/rules.yml
secomlint/entities/patterns.jsonl
secomlint-0.1.1.dist-info/LICENSE
secomlint-0.1.1.dist-info/METADATA
secomlint-0.1.1.dist-info/WHEEL
secomlint-0.1.1.dist-info/entry_points.txt
secomlint-0.1.1.dist-info/top_level.txt
secomlint-0.1.1.dist-info/RECORD
