Metadata-Version: 2.1
Name: secomlint
Version: 0.1.1
Summary: A linter for security commit messages
Home-page: https://github.com/tqrg/secomlint
Author: Sofia Reis
Author-email: sofiareis1994@gmail.com
License: MIT
License-File: LICENSE
Requires-Dist: spacy
Requires-Dist: pandas
Requires-Dist: pyyaml
